copy2hash/__init__.py
copy2hash/copy2hash.py
copy2hash-0.5.dist-info/LICENSE
copy2hash-0.5.dist-info/METADATA
copy2hash-0.5.dist-info/WHEEL
copy2hash-0.5.dist-info/entry_points.txt
copy2hash-0.5.dist-info/top_level.txt
copy2hash-0.5.dist-info/RECORD
