Metadata-Version: 2.1
Name: copy2hash
Version: 0.5
Summary: Copy or rename any file(s) to a hash-secured filename via terminal
Home-page: https://github.com/Anselmoo/copy2hash
Author: Anselm Hahn
Author-email: Anselm.Hahn@gmail.com
Maintainer: Anselm Hahn
Maintainer-email: Anselm.Hahn@gmail.com
License: MIT
Keywords: sha,sha256,hash,hash-key,data-science,database
Platform: UNKNOWN
Classifier: Development Status :: 5 - Production/Stable
Classifier: Environment :: Console
Classifier: Intended Audience :: Developers
Classifier: Intended Audience :: Information Technology
Classifier: Intended Audience :: Science/Research
Classifier: License :: OSI Approved :: MIT License
Classifier: Operating System :: MacOS
Classifier: Operating System :: Unix
Classifier: Programming Language :: Python :: 3
Classifier: Programming Language :: Python :: 3.6
Classifier: Programming Language :: Python :: 3.7
Classifier: Programming Language :: Python :: 3.8
Classifier: Topic :: System :: Shells
Classifier: Topic :: Database
Classifier: Topic :: Documentation
Classifier: Topic :: Utilities
Requires-Dist: dict2xml (>=1.7.0)
Requires-Dist: PyYAML (>=5.3.1)
Provides-Extra: testing
Requires-Dist: pipenv ; extra == 'testing'
